django_custom_logger/__init__.py
django_custom_logger/apps.py
django_custom_logger/config.py
django_custom_logger/custom_logging.py
django_custom_logger/middleware.py
django_custom_logger-0.1.0.dist-info/LICENSE
django_custom_logger-0.1.0.dist-info/METADATA
django_custom_logger-0.1.0.dist-info/WHEEL
django_custom_logger-0.1.0.dist-info/top_level.txt
django_custom_logger-0.1.0.dist-info/RECORD
